{
  "type": "GROUP",
"name": "Global Information",
"path": "",
"pathFormatted": "group_missing-name-b06d1",
"stats": {
    "name": "Global Information",
    "numberOfRequests": {
        "total": 7,
        "ok": 7,
        "ko": 0
    },
    "minResponseTime": {
        "total": 233,
        "ok": 233,
        "ko": 0
    },
    "maxResponseTime": {
        "total": 1065,
        "ok": 1065,
        "ko": 0
    },
    "meanResponseTime": {
        "total": 421,
        "ok": 421,
        "ko": 0
    },
    "standardDeviation": {
        "total": 282,
        "ok": 282,
        "ko": 0
    },
    "percentiles1": {
        "total": 260,
        "ok": 260,
        "ko": 0
    },
    "percentiles2": {
        "total": 455,
        "ok": 455,
        "ko": 0
    },
    "percentiles3": {
        "total": 904,
        "ok": 904,
        "ko": 0
    },
    "percentiles4": {
        "total": 1033,
        "ok": 1033,
        "ko": 0
    },
    "group1": {
        "name": "t < 800 ms",
        "count": 6,
        "percentage": 86
    },
    "group2": {
        "name": "800 ms < t < 1200 ms",
        "count": 1,
        "percentage": 14
    },
    "group3": {
        "name": "t > 1200 ms",
        "count": 0,
        "percentage": 0
    },
    "group4": {
        "name": "failed",
        "count": 0,
        "percentage": 0
    },
    "meanNumberOfRequestsPerSecond": {
        "total": 0.7777777777777778,
        "ok": 0.7777777777777778,
        "ko": 0
    }
},
"contents": {
"req_open-home-page-ba7f9": {
        "type": "REQUEST",
        "name": "Open Home Page",
"path": "Open Home Page",
"pathFormatted": "req_open-home-page-ba7f9",
"stats": {
    "name": "Open Home Page",
    "numberOfRequests": {
        "total": 1,
        "ok": 1,
        "ko": 0
    },
    "minResponseTime": {
        "total": 1065,
        "ok": 1065,
        "ko": 0
    },
    "maxResponseTime": {
        "total": 1065,
        "ok": 1065,
        "ko": 0
    },
    "meanResponseTime": {
        "total": 1065,
        "ok": 1065,
        "ko": 0
    },
    "standardDeviation": {
        "total": 0,
        "ok": 0,
        "ko": 0
    },
    "percentiles1": {
        "total": 1065,
        "ok": 1065,
        "ko": 0
    },
    "percentiles2": {
        "total": 1065,
        "ok": 1065,
        "ko": 0
    },
    "percentiles3": {
        "total": 1065,
        "ok": 1065,
        "ko": 0
    },
    "percentiles4": {
        "total": 1065,
        "ok": 1065,
        "ko": 0
    },
    "group1": {
        "name": "t < 800 ms",
        "count": 0,
        "percentage": 0
    },
    "group2": {
        "name": "800 ms < t < 1200 ms",
        "count": 1,
        "percentage": 100
    },
    "group3": {
        "name": "t > 1200 ms",
        "count": 0,
        "percentage": 0
    },
    "group4": {
        "name": "failed",
        "count": 0,
        "percentage": 0
    },
    "meanNumberOfRequestsPerSecond": {
        "total": 0.1111111111111111,
        "ok": 0.1111111111111111,
        "ko": 0
    }
}
    },"req_start-test-step-c813e": {
        "type": "REQUEST",
        "name": "Start Test Step 1",
"path": "Start Test Step 1",
"pathFormatted": "req_start-test-step-c813e",
"stats": {
    "name": "Start Test Step 1",
    "numberOfRequests": {
        "total": 1,
        "ok": 1,
        "ko": 0
    },
    "minResponseTime": {
        "total": 382,
        "ok": 382,
        "ko": 0
    },
    "maxResponseTime": {
        "total": 382,
        "ok": 382,
        "ko": 0
    },
    "meanResponseTime": {
        "total": 382,
        "ok": 382,
        "ko": 0
    },
    "standardDeviation": {
        "total": 0,
        "ok": 0,
        "ko": 0
    },
    "percentiles1": {
        "total": 382,
        "ok": 382,
        "ko": 0
    },
    "percentiles2": {
        "total": 382,
        "ok": 382,
        "ko": 0
    },
    "percentiles3": {
        "total": 382,
        "ok": 382,
        "ko": 0
    },
    "percentiles4": {
        "total": 382,
        "ok": 382,
        "ko": 0
    },
    "group1": {
        "name": "t < 800 ms",
        "count": 1,
        "percentage": 100
    },
    "group2": {
        "name": "800 ms < t < 1200 ms",
        "count": 0,
        "percentage": 0
    },
    "group3": {
        "name": "t > 1200 ms",
        "count": 0,
        "percentage": 0
    },
    "group4": {
        "name": "failed",
        "count": 0,
        "percentage": 0
    },
    "meanNumberOfRequestsPerSecond": {
        "total": 0.1111111111111111,
        "ok": 0.1111111111111111,
        "ko": 0
    }
}
    },"req_start-test-step-70033": {
        "type": "REQUEST",
        "name": "Start Test Step 1 Redirect 1",
"path": "Start Test Step 1 Redirect 1",
"pathFormatted": "req_start-test-step-70033",
"stats": {
    "name": "Start Test Step 1 Redirect 1",
    "numberOfRequests": {
        "total": 1,
        "ok": 1,
        "ko": 0
    },
    "minResponseTime": {
        "total": 528,
        "ok": 528,
        "ko": 0
    },
    "maxResponseTime": {
        "total": 528,
        "ok": 528,
        "ko": 0
    },
    "meanResponseTime": {
        "total": 528,
        "ok": 528,
        "ko": 0
    },
    "standardDeviation": {
        "total": 0,
        "ok": 0,
        "ko": 0
    },
    "percentiles1": {
        "total": 528,
        "ok": 528,
        "ko": 0
    },
    "percentiles2": {
        "total": 528,
        "ok": 528,
        "ko": 0
    },
    "percentiles3": {
        "total": 528,
        "ok": 528,
        "ko": 0
    },
    "percentiles4": {
        "total": 528,
        "ok": 528,
        "ko": 0
    },
    "group1": {
        "name": "t < 800 ms",
        "count": 1,
        "percentage": 100
    },
    "group2": {
        "name": "800 ms < t < 1200 ms",
        "count": 0,
        "percentage": 0
    },
    "group3": {
        "name": "t > 1200 ms",
        "count": 0,
        "percentage": 0
    },
    "group4": {
        "name": "failed",
        "count": 0,
        "percentage": 0
    },
    "meanNumberOfRequestsPerSecond": {
        "total": 0.1111111111111111,
        "ok": 0.1111111111111111,
        "ko": 0
    }
}
    },"req_start-test-step-1aea7": {
        "type": "REQUEST",
        "name": "Start Test Step 1 Redirect 2",
"path": "Start Test Step 1 Redirect 2",
"pathFormatted": "req_start-test-step-1aea7",
"stats": {
    "name": "Start Test Step 1 Redirect 2",
    "numberOfRequests": {
        "total": 1,
        "ok": 1,
        "ko": 0
    },
    "minResponseTime": {
        "total": 237,
        "ok": 237,
        "ko": 0
    },
    "maxResponseTime": {
        "total": 237,
        "ok": 237,
        "ko": 0
    },
    "meanResponseTime": {
        "total": 237,
        "ok": 237,
        "ko": 0
    },
    "standardDeviation": {
        "total": 0,
        "ok": 0,
        "ko": 0
    },
    "percentiles1": {
        "total": 237,
        "ok": 237,
        "ko": 0
    },
    "percentiles2": {
        "total": 237,
        "ok": 237,
        "ko": 0
    },
    "percentiles3": {
        "total": 237,
        "ok": 237,
        "ko": 0
    },
    "percentiles4": {
        "total": 237,
        "ok": 237,
        "ko": 0
    },
    "group1": {
        "name": "t < 800 ms",
        "count": 1,
        "percentage": 100
    },
    "group2": {
        "name": "800 ms < t < 1200 ms",
        "count": 0,
        "percentage": 0
    },
    "group3": {
        "name": "t > 1200 ms",
        "count": 0,
        "percentage": 0
    },
    "group4": {
        "name": "failed",
        "count": 0,
        "percentage": 0
    },
    "meanNumberOfRequestsPerSecond": {
        "total": 0.1111111111111111,
        "ok": 0.1111111111111111,
        "ko": 0
    }
}
    },"req_step-2-e31ad": {
        "type": "REQUEST",
        "name": "Step 2",
"path": "Step 2",
"pathFormatted": "req_step-2-e31ad",
"stats": {
    "name": "Step 2",
    "numberOfRequests": {
        "total": 1,
        "ok": 1,
        "ko": 0
    },
    "minResponseTime": {
        "total": 260,
        "ok": 260,
        "ko": 0
    },
    "maxResponseTime": {
        "total": 260,
        "ok": 260,
        "ko": 0
    },
    "meanResponseTime": {
        "total": 260,
        "ok": 260,
        "ko": 0
    },
    "standardDeviation": {
        "total": 0,
        "ok": 0,
        "ko": 0
    },
    "percentiles1": {
        "total": 260,
        "ok": 260,
        "ko": 0
    },
    "percentiles2": {
        "total": 260,
        "ok": 260,
        "ko": 0
    },
    "percentiles3": {
        "total": 260,
        "ok": 260,
        "ko": 0
    },
    "percentiles4": {
        "total": 260,
        "ok": 260,
        "ko": 0
    },
    "group1": {
        "name": "t < 800 ms",
        "count": 1,
        "percentage": 100
    },
    "group2": {
        "name": "800 ms < t < 1200 ms",
        "count": 0,
        "percentage": 0
    },
    "group3": {
        "name": "t > 1200 ms",
        "count": 0,
        "percentage": 0
    },
    "group4": {
        "name": "failed",
        "count": 0,
        "percentage": 0
    },
    "meanNumberOfRequestsPerSecond": {
        "total": 0.1111111111111111,
        "ok": 0.1111111111111111,
        "ko": 0
    }
}
    },"req_step-2-redirect-813ff": {
        "type": "REQUEST",
        "name": "Step 2 Redirect 1",
"path": "Step 2 Redirect 1",
"pathFormatted": "req_step-2-redirect-813ff",
"stats": {
    "name": "Step 2 Redirect 1",
    "numberOfRequests": {
        "total": 1,
        "ok": 1,
        "ko": 0
    },
    "minResponseTime": {
        "total": 233,
        "ok": 233,
        "ko": 0
    },
    "maxResponseTime": {
        "total": 233,
        "ok": 233,
        "ko": 0
    },
    "meanResponseTime": {
        "total": 233,
        "ok": 233,
        "ko": 0
    },
    "standardDeviation": {
        "total": 0,
        "ok": 0,
        "ko": 0
    },
    "percentiles1": {
        "total": 233,
        "ok": 233,
        "ko": 0
    },
    "percentiles2": {
        "total": 233,
        "ok": 233,
        "ko": 0
    },
    "percentiles3": {
        "total": 233,
        "ok": 233,
        "ko": 0
    },
    "percentiles4": {
        "total": 233,
        "ok": 233,
        "ko": 0
    },
    "group1": {
        "name": "t < 800 ms",
        "count": 1,
        "percentage": 100
    },
    "group2": {
        "name": "800 ms < t < 1200 ms",
        "count": 0,
        "percentage": 0
    },
    "group3": {
        "name": "t > 1200 ms",
        "count": 0,
        "percentage": 0
    },
    "group4": {
        "name": "failed",
        "count": 0,
        "percentage": 0
    },
    "meanNumberOfRequestsPerSecond": {
        "total": 0.1111111111111111,
        "ok": 0.1111111111111111,
        "ko": 0
    }
}
    },"req_step-2-redirect-18ebe": {
        "type": "REQUEST",
        "name": "Step 2 Redirect 2",
"path": "Step 2 Redirect 2",
"pathFormatted": "req_step-2-redirect-18ebe",
"stats": {
    "name": "Step 2 Redirect 2",
    "numberOfRequests": {
        "total": 1,
        "ok": 1,
        "ko": 0
    },
    "minResponseTime": {
        "total": 239,
        "ok": 239,
        "ko": 0
    },
    "maxResponseTime": {
        "total": 239,
        "ok": 239,
        "ko": 0
    },
    "meanResponseTime": {
        "total": 239,
        "ok": 239,
        "ko": 0
    },
    "standardDeviation": {
        "total": 0,
        "ok": 0,
        "ko": 0
    },
    "percentiles1": {
        "total": 239,
        "ok": 239,
        "ko": 0
    },
    "percentiles2": {
        "total": 239,
        "ok": 239,
        "ko": 0
    },
    "percentiles3": {
        "total": 239,
        "ok": 239,
        "ko": 0
    },
    "percentiles4": {
        "total": 239,
        "ok": 239,
        "ko": 0
    },
    "group1": {
        "name": "t < 800 ms",
        "count": 1,
        "percentage": 100
    },
    "group2": {
        "name": "800 ms < t < 1200 ms",
        "count": 0,
        "percentage": 0
    },
    "group3": {
        "name": "t > 1200 ms",
        "count": 0,
        "percentage": 0
    },
    "group4": {
        "name": "failed",
        "count": 0,
        "percentage": 0
    },
    "meanNumberOfRequestsPerSecond": {
        "total": 0.1111111111111111,
        "ok": 0.1111111111111111,
        "ko": 0
    }
}
    }
}

}