{
    "name": "Global Information",
    "numberOfRequests": {
        "total": 10,
        "ok": 9,
        "ko": 1
    },
    "minResponseTime": {
        "total": 216,
        "ok": 216,
        "ko": 224
    },
    "maxResponseTime": {
        "total": 1047,
        "ok": 1047,
        "ko": 224
    },
    "meanResponseTime": {
        "total": 333,
        "ok": 345,
        "ko": 224
    },
    "standardDeviation": {
        "total": 250,
        "ok": 261,
        "ko": 0
    },
    "percentiles1": {
        "total": 228,
        "ok": 228,
        "ko": 224
    },
    "percentiles2": {
        "total": 233,
        "ok": 233,
        "ko": 224
    },
    "percentiles3": {
        "total": 795,
        "ok": 823,
        "ko": 224
    },
    "percentiles4": {
        "total": 997,
        "ok": 1002,
        "ko": 224
    },
    "group1": {
        "name": "t < 800 ms",
        "count": 8,
        "percentage": 80
    },
    "group2": {
        "name": "800 ms < t < 1200 ms",
        "count": 1,
        "percentage": 10
    },
    "group3": {
        "name": "t > 1200 ms",
        "count": 0,
        "percentage": 0
    },
    "group4": {
        "name": "failed",
        "count": 1,
        "percentage": 10
    },
    "meanNumberOfRequestsPerSecond": {
        "total": 1.1111111111111112,
        "ok": 1.0,
        "ko": 0.1111111111111111
    }
}